stencila_plugin-2.0.0a34.dist-info/METADATA
stencila_plugin-2.0.0a34.dist-info/WHEEL
stencila_plugin/__init__.py
stencila_plugin/assistant.py
stencila_plugin/kernel.py
stencila_plugin/plugin.py
stencila_plugin/testing.py
stencila_plugin-2.0.0a34.dist-info/RECORD
